Workbook

Sheet Report1
A1: Column 1 | B1: Column 2 | C1: Column 3 | D1: Column 4 | E1: Column 5 | F1: Column 6 | G1: Call | H1: Schedule | I1: Complete | J1: Column 7 | K1: Column 8 | L1: Column 9
A2: WO# | B2: Prop-Unit | C2: Status | D2: Category | E2: Brief Desc | F2: Tenant | G2: Date | H2: Date | I2: Date | K2: Vendor | L2: Amount
A3: 270 | B3: rheing-533-2C | C3: Work Completed | D3: Plumbing | E3: Bathroom leak/Kitchen faucet | G3: 40064.438 | I3: 40633.801 | J3: =IF(DAYS(I3,G3)<0,0,DAYS(I3,G3)) -> 569 | L3: 0
A4: 272 | B4: rheing-555-6C | C4: Work Completed | D4: Appliances | E4: Refrigerator | G4: 40064.451 | I4: 40633.803 | J4: =IF(DAYS(I4,G4)<0,0,DAYS(I4,G4)) -> 569 | K4: domestic - Domestic Air Conditioning Service, Inc | L4: 0
A5: 273 | B5: rheing-555-6C | C5: Work Completed | D5: Electrical | E5: Kitchen light/ Stove hood fan | G5: 40064.463 | I5: 40633.804 | J5: =IF(DAYS(I5,G5)<0,0,DAYS(I5,G5)) -> 569 | L5: 0
A6: 274 | B6: rheing-533-4J | C6: Work Completed | D6: Painting and Plastering | E6: Painting | G6: 40064.478 | I6: 40633.803 | J6: =IF(DAYS(I6,G6)<0,0,DAYS(I6,G6)) -> 569 | K6: gpspaint - GPS Painting of NY | L6: 0
A7: 275 | B7: rheing-533-5C | C7: Work Completed | D7: Miscellaneous | E7: Intercom | G7: 40064.494 | I7: 40633.803 | J7: =IF(DAYS(I7,G7)<0,0,DAYS(I7,G7)) -> 569 | K7: mgservic - MG Service and Installations, Inc | L7: 0
A8: 276 | B8: rheing-533-4D | C8: Work Completed | D8: Miscellaneous | E8: Bathroom soap dish | G8: 40064.498 | I8: 40633.802 | J8: =IF(DAYS(I8,G8)<0,0,DAYS(I8,G8)) -> 569 | L8: 0
A9: 277 | B9: rheing-555-6I | C9: Work Completed | D9: Flooring | E9: Bathroom tiles/light | G9: 40064.503 | I9: 40634.434 | J9: =IF(DAYS(I9,G9)<0,0,DAYS(I9,G9)) -> 570 | L9: 0
A10: 278 | B10: rheing-555-5A | C10: Work Completed | D10: Miscellaneous | E10: Intercom | G10: 40064.513 | I10: 40633.803 | J10: =IF(DAYS(I10,G10)<0,0,DAYS(I10,G10)) -> 569 | K10: mgservic - MG Service and Installations, Inc | L10: 0
A11: 279 | B11: rheing-555-2C | C11: Work Completed | D11: Appliances | E11: Refrigerator | G11: 40064.6 | I11: 40633.803 | J11: =IF(DAYS(I11,G11)<0,0,DAYS(I11,G11)) -> 569 | L11: 0
A12: 289 | B12: rheing-533-2E | C12: Work Completed | D12: Plumbing | E12: Kitchen sink | G12: 40066.668 | I12: 40106.684 | J12: =IF(DAYS(I12,G12)<0,0,DAYS(I12,G12)) -> 40 | L12: 0
A13: 302 | B13: rheing-555-5C | C13: Work Completed | D13: Extermination | E13: MICE | F13: Morejon,Lucy | G13: 40072.435 | I13: 40085.671 | J13: =IF(DAYS(I13,G13)<0,0,DAYS(I13,G13)) -> 13 | L13: 0
A14: 303 | B14: rheing-533-5B | C14: Work Completed | D14: Plumbing | E14: PLUMBING | F14: Matias,Ramona | G14: 40072.436 | I14: 40085.672 | J14: =IF(DAYS(I14,G14)<0,0,DAYS(I14,G14)) -> 13 | L14: 0
A15: 332 | B15: rheing-533-4F | C15: Work Completed | D15: Plumbing | E15: Bathroom Sink leaking | G15: 40077.401 | I15: 40085.671 | J15: =IF(DAYS(I15,G15)<0,0,DAYS(I15,G15)) -> 8 | K15: mtorres - | L15: 0
A16: 343 | B16: rheing-533-2I | C16: Work Completed | D16: Appliances | E16: Air condition | G16: 40078.646 | I16: 40092.447 | J16: =IF(DAYS(I16,G16)<0,0,DAYS(I16,G16)) -> 14 | L16: 0
A17: 348 | B17: rheing-533-4C | C17: Work Completed | D17: Plumbing | E17: Bathroom | G17: 40079.54 | I17: 40092.465 | J17: =IF(DAYS(I17,G17)<0,0,DAYS(I17,G17)) -> 13 | L17: 0
A18: 354 | B18: rheing-533-4F | C18: Work Completed | D18: Miscellaneous | E18: Bathroom sink | G18: 40079.644 | I18: 40112.628 | J18: =IF(DAYS(I18,G18)<0,0,DAYS(I18,G18)) -> 33 | L18: 0
A19: 414 | B19: rheing-533-4J | C19: Work Completed | D19: Plumbing | E19: Bathroom/bedroom leaks | G19: 40085.531 | I19: 40130.619 | J19: =IF(DAYS(I19,G19)<0,0,DAYS(I19,G19)) -> 45 | L19: 0
A20: 415 | B20: rheing-555-2D | C20: Work Completed | D20: Miscellaneous | E20: Intercom | G20: 40085.551 | I20: 40142.514 | J20: =IF(DAYS(I20,G20)<0,0,DAYS(I20,G20)) -> 57 | L20: 0
A21: 418 | B21: rheing-533-5C | C21: Work Completed | D21: Plumbing | E21: Bathroom Leak | G21: 40085.649 | I21: 40112.629 | J21: =IF(DAYS(I21,G21)<0,0,DAYS(I21,G21)) -> 27 | L21: 0
A22: 427 | B22: rheing-555-5C | C22: Work Completed | D22: Plumbing | E22: Bathroom sink | G22: 40091.456 | I22: 40106.688 | J22: =IF(DAYS(I22,G22)<0,0,DAYS(I22,G22)) -> 15 | L22: 0
A23: 437 | B23: rheing-555-6C | C23: Work Completed | D23: Miscellaneous | E23: Bathroom | G23: 40092.421 | I23: 40106.688 | J23: =IF(DAYS(I23,G23)<0,0,DAYS(I23,G23)) -> 14 | L23: 0
A24: 454 | B24: rheing-533-4E | C24: Work Completed | D24: Heating | E24: Bedroom: heat zone valve | G24: 40095.365 | I24: 40112.629 | J24: =IF(DAYS(I24,G24)<0,0,DAYS(I24,G24)) -> 17 | L24: 0
A25: 465 | B25: rheing-555-6E | C25: Work Completed | D25: Windows | E25: Windows | G25: 40095.644 | I25: 40112.619 | J25: =IF(DAYS(I25,G25)<0,0,DAYS(I25,G25)) -> 17 | L25: 0
A26: 468 | B26: rheing-533-4F | C26: Work Completed | D26: Plumbing | E26: Bathroom Sink | G26: 40095.658 | I26: 40112.628 | J26: =IF(DAYS(I26,G26)<0,0,DAYS(I26,G26)) -> 17 | L26: 0
A27: 475 | B27: rheing-555-5G | C27: Work Completed | D27: Plumbing | E27: Bathroom toilet | G27: 40099.654 | I27: 40112.622 | J27: =IF(DAYS(I27,G27)<0,0,DAYS(I27,G27)) -> 13 | L27: 0
... A38: 530 | B38: rheing-555-3D | C38: Work Completed | D38: Heating | E38: Heat | G38: 40108.676 | I38: 40116.646 | J38: =IF(DAYS(I38,G38)<0,0,DAYS(I38,G38)) -> 8 | L38: 0
A39: 550 | B39: rheing-555-5I | C39: Work Completed | D39: Appliances | E39: REFRIGERATOR | G39: 40113.544 | I39: 40130.619 | J39: =IF(DAYS(I39,G39)<0,0,DAYS(I39,G39)) -> 17 | K39: domestic - Domestic Air Conditioning Service, Inc | L39: 0
A40: 552 | B40: rheing-555-6A | C40: Work Completed | D40: Plumbing | E40: BATHROOM SINK | G40: 40113.56 | I40: 40130.616 | J40: =IF(DAYS(I40,G40)<0,0,DAYS(I40,G40)) -> 17 | L40: 0
A41: 567 | B41: rheing-555-4G | C41: Work Completed | D41: Heating | E41: BROKEN HEATER | G41: 40116.395 | I41: 40253.687 | J41: =IF(DAYS(I41,G41)<0,0,DAYS(I41,G41)) -> 137 | L41: 0
A42: 568 | B42: rheing-533-2G | C42: Work Completed | D42: Doors and Locks | E42: LOCKS / DOORS | G42: 40116.401 | I42: 40126.408 | J42: =IF(DAYS(I42,G42)<0,0,DAYS(I42,G42)) -> 10 | L42: 0
A43: 570 | B43: rheing-555-6A | C43: Work Completed | D43: Miscellaneous | E43: BATHROOM | G43: 40116.502 | I43: 40130.616 | J43: =IF(DAYS(I43,G43)<0,0,DAYS(I43,G43)) -> 14 | L43: 0
A44: 571 | B44: rheing-533-3H | C44: Work Completed | D44: Heating | E44: HEAT | G44: 40116.505 | I44: 40130.618 | J44: =IF(DAYS(I44,G44)<0,0,DAYS(I44,G44)) -> 14 | L44: 0
A45: 572 | B45: rheing-533-2G | C45: Work Completed | D45: Painting and Plastering | E45: LIVINGROOM CEILING | G45: 40116.508 | I45: 40126.398 | J45: =IF(DAYS(I45,G45)<0,0,DAYS(I45,G45)) -> 10 | L45: 0
A46: 578 | B46: rheing-555-5C | C46: Work Completed | D46: Painting and Plastering | E46: KITCHEN WALL | G46: 40116.674 | I46: 40130.617 | J46: =IF(DAYS(I46,G46)<0,0,DAYS(I46,G46)) -> 14 | L46: 0
A47: 596 | B47: rheing-533-2B | C47: Work Completed | D47: Plumbing | E47: Leaking | G47: 40123.668 | I47: 40253.688 | J47: =IF(DAYS(I47,G47)<0,0,DAYS(I47,G47)) -> 130 | L47: 0
A48: 605 | B48: rheing-533-2B | C48: Work Completed | D48: Plumbing | E48: LEAK | F48: Mero,Martha | G48: 40127.416 | I48: 40253.688 | J48: =IF(DAYS(I48,G48)<0,0,DAYS(I48,G48)) -> 126 | L48: 0
A49: 618 | B49: rheing-533-2B | C49: Work Completed | D49: Plumbing | E49: leak | F49: Mero,Martha | G49: 40130.659 | I49: 40142.515 | J49: =IF(DAYS(I49,G49)<0,0,DAYS(I49,G49)) -> 12 | L49: 0
A50: 650 | B50: rheing-555-2D | C50: Work Completed | D50: Plumbing | E50: TOILET | G50: 40134.72 | I50: 40142.515 | J50: =IF(DAYS(I50,G50)<0,0,DAYS(I50,G50)) -> 8 | L50: 0
A51: 663 | B51: rheing-533-6J | C51: Work Completed | D51: Plumbing | E51: Bathroom sink | G51: 40135.456 | I51: 40142.516 | J51: =IF(DAYS(I51,G51)<0,0,DAYS(I51,G51)) -> 7 | L51: 0
A52: 664 | B52: rheing-533-4H | C52: Work Completed | D52: Plumbing | E52: 917 620-1443 | G52: 40135.459 | I52: 40142.517 | J52: =IF(DAYS(I52,G52)<0,0,DAYS(I52,G52)) -> 7 | L52: 0
A53: 668 | B53: rheing-555-6H | C53: Work Completed | D53: Plumbing | E53: SINK | G53: 40135.512 | I53: 40142.516 | J53: =IF(DAYS(I53,G53)<0,0,DAYS(I53,G53)) -> 7 | L53: 0
A54: 671 | B54: rheing-533-4E | C54: Work Completed | D54: Heating | E54: HEAT | G54: 40135.613 | I54: 40253.688 | J54: =IF(DAYS(I54,G54)<0,0,DAYS(I54,G54)) -> 118 | L54: 0
A55: 678 | B55: rheing-533-5C | C55: Work Completed | D55: Doors and Locks | E55: DOOR LOCK | G55: 40136.722 | I55: 40155.755 | J55: =IF(DAYS(I55,G55)<0,0,DAYS(I55,G55)) -> 19 | L55: 0
A56: 690 | B56: rheing-533-3C | C56: Work Completed | D56: Plumbing | E56: SHOWER HEAD | G56: 40142.507 | I56: 40170.679 | J56: =IF(DAYS(I56,G56)<0,0,DAYS(I56,G56)) -> 28 | L56: 0
A57: 691 | B57: rheing-555-2E | C57: Work Completed | D57: Heating | E57: HEAT VALVE | G57: 40142.509 | I57: 40155.754 | J57: =IF(DAYS(I57,G57)<0,0,DAYS(I57,G57)) -> 13 | L57: 0
A58: 701 | B58: rheing-533-4J | C58: Work Completed | D58: Plumbing | E58: LEAK | G58: 40149.608 | I58: 40171.619 | J58: =IF(DAYS(I58,G58)<0,0,DAYS(I58,G58)) -> 22 | L58: 0
A59: 702 | B59: rheing-555-4I | C59: Work Completed | D59: Doors and Locks | E59: LOCKS | G59: 40149.613 | I59: 40171.62 | J59: =IF(DAYS(I59,G59)<0,0,DAYS(I59,G59)) -> 22 | L59: 0
A60: 703 | B60: rheing-555-2A | C60: Work Completed | D60: Plumbing | E60: LEAK | G60: 40149.617 | I60: 40170.679 | J60: =IF(DAYS(I60,G60)<0,0,DAYS(I60,G60)) -> 21 | L60: 0
A61: 712 | B61: rheing-533-6I | C61: Work Completed | D61: Plumbing | E61: SINK | G61: 40149.669 | I61: 40171.619 | J61: =IF(DAYS(I61,G61)<0,0,DAYS(I61,G61)) -> 22 | L61: 0
... A107: 1079 | B107: rheing-555-5F | C107: Work Completed | D107: Plumbing | E107: LEAKS | G107: 40213.671 | I107: 40213.671 | J107: =IF(DAYS(I107,G107)<0,0,DAYS(I107,G107)) -> 0 | L107: 0
A108: 1090 | B108: rheing-533-5C | C108: Work Completed | D108: Appliances | E108: REFRIGERATOR | F108: C/O Rhonda Milton,New York Foundation for Senior Citizens | G108: 40214.44 | I108: 40253.69 | J108: =IF(DAYS(I108,G108)<0,0,DAYS(I108,G108)) -> 39 | L108: 0
A109: 1096 | B109: rheing-555-5F | C109: Work Completed | D109: Plumbing | E109: PIPE LOOSE IN THE BATHROOM | G109: 40217.631 | I109: 40233.581 | J109: =IF(DAYS(I109,G109)<0,0,DAYS(I109,G109)) -> 16 | L109: 0
A110: 1099 | B110: rheing-555-6I | C110: Work Completed | D110: Plumbing | E110: BROKEN TOILET | G110: 40217.642 | I110: 40233.582 | J110: =IF(DAYS(I110,G110)<0,0,DAYS(I110,G110)) -> 16 | L110: 0
A111: 1109 | B111: rheing-533-5H | C111: Work Completed | D111: Plumbing | E111: TOILET TANK | G111: 40219.516 | I111: 40219.516 | J111: =IF(DAYS(I111,G111)<0,0,DAYS(I111,G111)) -> 0 | L111: 0
A112: 1119 | B112: rheing-555-6C | C112: Work Completed | D112: Appliances | E112: STOVE LEAKING GAS | G112: 40221.559 | I112: 40247.604 | J112: =IF(DAYS(I112,G112)<0,0,DAYS(I112,G112)) -> 26 | L112: 0
A113: 1125 | B113: rheing-533-4G | C113: Work Completed | D113: Miscellaneous | E113: CULK BATHTUB | G113: 40221.592 | I113: 40247.604 | J113: =IF(DAYS(I113,G113)<0,0,DAYS(I113,G113)) -> 26 | L113: 0
A114: 1153 | B114: rheing-533-5C | C114: Work Completed | D114: Plumbing | E114: SHOWER LEAKING | G114: 40227.699 | I114: 40247.604 | J114: =IF(DAYS(I114,G114)<0,0,DAYS(I114,G114)) -> 20 | L114: 0
A115: 1159 | B115: rheing-533-5F | C115: Work Completed | D115: Windows | E115: BROKEN WINDOW | G115: 40228.637 | I115: 40253.69 | J115: =IF(DAYS(I115,G115)<0,0,DAYS(I115,G115)) -> 25 | L115: 0
A116: 1171 | B116: rheing-555-2C | C116: Work Completed | D116: Plumbing | E116: LEAKING SINK | G116: 40233.453 | I116: 40253.69 | J116: =IF(DAYS(I116,G116)<0,0,DAYS(I116,G116)) -> 20 | L116: 0
A117: 1172 | B117: rheing-533-2H | C117: Work Completed | D117: Heating | E117: HEATING LINE | G117: 40233.484 | I117: 40233.484 | J117: =IF(DAYS(I117,G117)<0,0,DAYS(I117,G117)) -> 0 | L117: 0
A118: 1173 | B118: rheing-533-3J | C118: Work Completed | D118: Doors and Locks | E118: BROKEN DOOR | G118: 40233.487 | I118: 40233.487 | J118: =IF(DAYS(I118,G118)<0,0,DAYS(I118,G118)) -> 0 | L118: 0
A119: 1193 | B119: rheing-555-5D | C119: Work Completed | D119: Plumbing | E119: LEAK | G119: 40240.561 | I119: 40253.691 | J119: =IF(DAYS(I119,G119)<0,0,DAYS(I119,G119)) -> 13 | L119: 0
A120: 1204 | B120: rheing-533-2B | C120: Work Completed | D120: Plumbing | E120: TOILET CLOG | G120: 40241.648 | I120: 40253.691 | J120: =IF(DAYS(I120,G120)<0,0,DAYS(I120,G120)) -> 12 | L120: 0
... A123: 1207 | B123: rheing-533-2B | C123: Work Completed | D123: Plumbing | E123: TOILET CLOG | G123: 40241.648 | I123: 40253.692 | J123: =IF(DAYS(I123,G123)<0,0,DAYS(I123,G123)) -> 12 | L123: 0
A124: 1212 | B124: rheing-533-5F | C124: Work Completed | D124: Windows | E124: WINDOWS | G124: 40245.539 | I124: 40253.692 | J124: =IF(DAYS(I124,G124)<0,0,DAYS(I124,G124)) -> 8 | K124: samthegl - Sam The Glazier Corp. | L124: 0
A125: 1213 | B125: rheing | C125: Work Completed | D125: Windows | E125: GLASS DOOR | G125: 40245.544 | I125: 40253.692 | J125: =IF(DAYS(I125,G125)<0,0,DAYS(I125,G125)) -> 8 | K125: samthegl - Sam The Glazier Corp. | L125: 0
A126: 1246 | B126: rheing-555-5H | C126: Canceled | D126: Plumbing | E126: TOILET CLOG | G126: 40248.687 | J126: =IF(DAYS(I126,G126)<0,0,DAYS(I126,G126)) -> 0 | L126: 0
A127: 1247 | B127: rheing-555-3F | C127: Work Completed | D127: Plumbing | E127: SHOWER HEAD | G127: 40248.69 | I127: 40259.423 | J127: =IF(DAYS(I127,G127)<0,0,DAYS(I127,G127)) -> 11 | L127: 0
A128: 1248 | B128: rheing-555-5I | C128: Work Completed | D128: Electrical | E128: LIGHTS | G128: 40248.692 | I128: 40253.693 | J128: =IF(DAYS(I128,G128)<0,0,DAYS(I128,G128)) -> 5 | L128: 0
A129: 1249 | B129: rheing-555-5I | C129: Work Completed | D129: Electrical | E129: LIGHTS | G129: 40248.692 | I129: 40253.693 | J129: =IF(DAYS(I129,G129)<0,0,DAYS(I129,G129)) -> 5 | L129: 0
A130: 1261 | B130: rheing-533-2C | C130: Work Completed | D130: Plumbing | E130: SINK | F130: Matias,Linda | G130: 40249.664 | I130: 40641.462 | J130: =IF(DAYS(I130,G130)<0,0,DAYS(I130,G130)) -> 392 | L130: 0
A131: 1266 | B131: rheing-555-2C | C131: Work Completed | D131: Plumbing | E131: CLOG TUB | F131: Berroteran,Jose | G131: 40252.474 | I131: 40269.638 | J131: =IF(DAYS(I131,G131)<0,0,DAYS(I131,G131)) -> 17 | L131: 0
A132: 1279 | B132: rheing-555-5F | C132: Work Completed | D132: Plumbing | E132: SINK PIPE/LEAKS/ WALL CRACKING | G132: 40254.488 | I132: 40269.637 | J132: =IF(DAYS(I132,G132)<0,0,DAYS(I132,G132)) -> 15 | L132: 0
A133: 1307 | B133: rheing-555-2C | C133: Work Completed | D133: Electrical | E133: eletrical | G133: 40261.59 | I133: 40261.59 | J133: =IF(DAYS(I133,G133)<0,0,DAYS(I133,G133)) -> 0 | L133: 0
A134: 1308 | B134: rheing-533-4G | C134: Work Completed | D134: Electrical | E134: Eletrical | G134: 40261.592 | I134: 40269.43 | J134: =IF(DAYS(I134,G134)<0,0,DAYS(I134,G134)) -> 8 | L134: 0
A135: 1309 | B135: rheing-533-6G | C135: Work Completed | D135: Doors and Locks | E135: Door | G135: 40261.598 | I135: 40261.598 | J135: =IF(DAYS(I135,G135)<0,0,DAYS(I135,G135)) -> 0 | L135: 0
A136: 1310 | B136: rheing-533-5I | C136: Work Completed | D136: Electrical | E136: eletrical | G136: 40261.6 | I136: 40261.6 | J136: =IF(DAYS(I136,G136)<0,0,DAYS(I136,G136)) -> 0 | L136: 0
A137: 1311 | B137: rheing-555-3D | C137: Work Completed | D137: Windows | E137: window | G137: 40261.607 | I137: 40261.607 | J137: =IF(DAYS(I137,G137)<0,0,DAYS(I137,G137)) -> 0 | L137: 0
A138: 1312 | B138: rheing-555-2C | C138: Work Completed | D138: Plumbing | E138: bathroom | G138: 40261.608 | I138: 40261.608 | J138: =IF(DAYS(I138,G138)<0,0,DAYS(I138,G138)) -> 0 | L138: 0
A139: 1314 | B139: rheing-533-2B | C139: Work Completed | D139: Carpentry | E139: leak | G139: 40261.64 | I139: 40261.64 | J139: =IF(DAYS(I139,G139)<0,0,DAYS(I139,G139)) -> 0 | L139: 0
A140: 1315 | B140: rheing-533-2G | C140: Work Completed | D140: Plumbing | E140: toilet | G140: 40261.653 | I140: 40261.653 | J140: =IF(DAYS(I140,G140)<0,0,DAYS(I140,G140)) -> 0 | L140: 0
A141: 1316 | B141: rheing-533-2C | C141: Work Completed | D141: Heating | E141: leak | G141: 40261.655 | I141: 40261.655 | J141: =IF(DAYS(I141,G141)<0,0,DAYS(I141,G141)) -> 0 | L141: 0
A142: 1317 | B142: rheing-533-3J | C142: Work Completed | D142: Doors and Locks | E142: door | G142: 40261.668 | I142: 40261.668 | J142: =IF(DAYS(I142,G142)<0,0,DAYS(I142,G142)) -> 0 | L142: 0
A143: 1318 | B143: rheing-533-6G | C143: Work Completed | D143: Electrical | E143: eletrical | G143: 40261.669 | I143: 40261.669 | J143: =IF(DAYS(I143,G143)<0,0,DAYS(I143,G143)) -> 0 | L143: 0
... A166: 1473 | B166: rheing-533-6C | C166: Work Completed | D166: Plumbing | E166: CLOG TOILET | G166: 40287.465 | I166: 40287.465 | J166: =IF(DAYS(I166,G166)<0,0,DAYS(I166,G166)) -> 0 | L166: 0
A167: 1474 | B167: rheing-533-2B | C167: Work Completed | D167: Doors and Locks | G167: 40287.475 | I167: 40287.475 | J167: =IF(DAYS(I167,G167)<0,0,DAYS(I167,G167)) -> 0 | L167: 0
A168: 1488 | B168: rheing-533-6A | C168: Work Completed | D168: Flooring | E168: TILES/CEILING | G168: 40291.561 | I168: 40312.426 | J168: =IF(DAYS(I168,G168)<0,0,DAYS(I168,G168)) -> 21 | L168: 0
A169: 1505 | B169: rheing-555-5H | C169: Work Completed | D169: Painting and Plastering | E169: PAINT APT | G169: 40295.601 | I169: 40381.744 | J169: =IF(DAYS(I169,G169)<0,0,DAYS(I169,G169)) -> 86 | L169: 0
A170: 1517 | B170: rheing-533-4F | C170: Work Completed | D170: Doors and Locks | E170: DOOR | G170: 40301.471 | I170: 40343.602 | J170: =IF(DAYS(I170,G170)<0,0,DAYS(I170,G170)) -> 42 | L170: 0
A171: 1605 | B171: rheing-555-3H | C171: Work Completed | D171: Plumbing | E171: DRINE LINE | G171: 40308.578 | I171: 40308.578 | J171: =IF(DAYS(I171,G171)<0,0,DAYS(I171,G171)) -> 0 | L171: 0
A172: 1606 | B172: rheing-555-5F | C172: Work Completed | D172: Plumbing | E172: UNCLOG SINK | G172: 40308.582 | I172: 40308.582 | J172: =IF(DAYS(I172,G172)<0,0,DAYS(I172,G172)) -> 0 | L172: 0
A173: 1607 | B173: rheing-555-3H | C173: Work Completed | D173: Plumbing | E173: CLOG SINK | G173: 40308.584 | I173: 40308.584 | J173: =IF(DAYS(I173,G173)<0,0,DAYS(I173,G173)) -> 0 | L173: 0
A174: 1608 | B174: rheing-555-3G | C174: Work Completed | D174: Plumbing | E174: DRAIN LINE | G174: 40308.586 | I174: 40308.586 | J174: =IF(DAYS(I174,G174)<0,0,DAYS(I174,G174)) -> 0 | L174: 0
A175: 1609 | B175: rheing-555-3G | C175: Work Completed | D175: Plumbing | E175: FILL VALVE/CULK BATHROOM SINK | G175: 40308.589 | I175: 40308.589 | J175: =IF(DAYS(I175,G175)<0,0,DAYS(I175,G175)) -> 0 | L175: 0
A176: 1610 | B176: rheing-533-6G | C176: Work Completed | D176: Plumbing | E176: HEAT RISER | G176: 40308.598 | I176: 40308.598 | J176: =IF(DAYS(I176,G176)<0,0,DAYS(I176,G176)) -> 0 | L176: 0
A177: 1611 | B177: rheing-533-6B | C177: Work Completed | D177: Heating | E177: FLOAT VENT / 2 WATTS RELULATOR | G177: 40308.608 | I177: 40308.608 | J177: =IF(DAYS(I177,G177)<0,0,DAYS(I177,G177)) -> 0 | L177: 0
A178: 1616 | B178: rheing-555-6H | C178: Work Completed | D178: Flooring | E178: TILES | G178: 40309.662 | I178: 40343.602 | J178: =IF(DAYS(I178,G178)<0,0,DAYS(I178,G178)) -> 34 | L178: 0
A179: 1644 | B179: rheing-555-3D | C179: Work Completed | D179: Plumbing | E179: BATHROOM TUB | G179: 40316.386 | I179: 40354.565 | J179: =IF(DAYS(I179,G179)<0,0,DAYS(I179,G179)) -> 38 | L179: 0
...

Sheet Categories
A1: Category | B1: Orders Filed | C1: Cost | D1: Orders Completed | E1: Percent Completed | F1: Average TTC
A2: {=UNIQUE(Report1!D3:D6181)} -> Plumbing | B2: =COUNTIF(Report1!D:D,A2) -> 2087 | C2: =AVERAGEIFS(Report1!L:L,Report1!L:L,">0",Report1!D:D,A2) -> 161.04019 | D2: =COUNTIFS(Report1!I:I,">0",Report1!D:D,A2) -> 1948 | E2: =D2/B2 -> 0.93339722 | F2: =AVERAGEIFS(Report1!J:J,Report1!I:I,">0",Report1!D:D,A2) -> 71.638604
A3: Appliances | B3: =COUNTIF(Report1!D:D,A3) -> 341 | C3: =AVERAGEIFS(Report1!L:L,Report1!L:L,">0",Report1!D:D,A3) -> 157.73574 | D3: =COUNTIFS(Report1!I:I,">0",Report1!D:D,A3) -> 294 | E3: =D3/B3 -> 0.86217009 | F3: =AVERAGEIFS(Report1!J:J,Report1!I:I,">0",Report1!D:D,A3) -> 461.96939
A4: Electrical | B4: =COUNTIF(Report1!D:D,A4) -> 506 | C4: =AVERAGEIFS(Report1!L:L,Report1!L:L,">0",Report1!D:D,A4) -> 876.36111 | D4: =COUNTIFS(Report1!I:I,">0",Report1!D:D,A4) -> 469 | E4: =D4/B4 -> 0.92687747 | F4: =AVERAGEIFS(Report1!J:J,Report1!I:I,">0",Report1!D:D,A4) -> 73.599147
A5: Painting and Plastering | B5: =COUNTIF(Report1!D:D,A5) -> 220 | C5: =AVERAGEIFS(Report1!L:L,Report1!L:L,">0",Report1!D:D,A5) -> 133.11154 | D5: =COUNTIFS(Report1!I:I,">0",Report1!D:D,A5) -> 172 | E5: =D5/B5 -> 0.78181818 | F5: =AVERAGEIFS(Report1!J:J,Report1!I:I,">0",Report1!D:D,A5) -> 214.58721
A6: Miscellaneous | B6: =COUNTIF(Report1!D:D,A6) -> 37 | C6: =AVERAGEIFS(Report1!L:L,Report1!L:L,">0",Report1!D:D,A6) -> #DIV/0! | D6: =COUNTIFS(Report1!I:I,">0",Report1!D:D,A6) -> 37 | E6: =D6/B6 -> 1 | F6: =AVERAGEIFS(Report1!J:J,Report1!I:I,">0",Report1!D:D,A6) -> 178
A7: Flooring | B7: =COUNTIF(Report1!D:D,A7) -> 83 | C7: =AVERAGEIFS(Report1!L:L,Report1!L:L,">0",Report1!D:D,A7) -> 2.42 | D7: =COUNTIFS(Report1!I:I,">0",Report1!D:D,A7) -> 62 | E7: =D7/B7 -> 0.74698795 | F7: =AVERAGEIFS(Report1!J:J,Report1!I:I,">0",Report1!D:D,A7) -> 220.67742
A8: Extermination | B8: =COUNTIF(Report1!D:D,A8) -> 147 | C8: =AVERAGEIFS(Report1!L:L,Report1!L:L,">0",Report1!D:D,A8) -> 1067.63 | D8: =COUNTIFS(Report1!I:I,">0",Report1!D:D,A8) -> 115 | E8: =D8/B8 -> 0.78231293 | F8: =AVERAGEIFS(Report1!J:J,Report1!I:I,">0",Report1!D:D,A8) -> 303.89565
A9: Heating | B9: =COUNTIF(Report1!D:D,A9) -> 215 | C9: =AVERAGEIFS(Report1!L:L,Report1!L:L,">0",Report1!D:D,A9) -> 711.6995 | D9: =COUNTIFS(Report1!I:I,">0",Report1!D:D,A9) -> 199 | E9: =D9/B9 -> 0.9255814 | F9: =AVERAGEIFS(Report1!J:J,Report1!I:I,">0",Report1!D:D,A9) -> 152.13568
A10: Windows | B10: =COUNTIF(Report1!D:D,A10) -> 297 | C10: =AVERAGEIFS(Report1!L:L,Report1!L:L,">0",Report1!D:D,A10) -> 2.4671429 | D10: =COUNTIFS(Report1!I:I,">0",Report1!D:D,A10) -> 271 | E10: =D10/B10 -> 0.91245791 | F10: =AVERAGEIFS(Report1!J:J,Report1!I:I,">0",Report1!D:D,A10) -> 713.631
A11: Doors and Locks | B11: =COUNTIF(Report1!D:D,A11) -> 432 | C11: =AVERAGEIFS(Report1!L:L,Report1!L:L,">0",Report1!D:D,A11) -> 183.372 | D11: =COUNTIFS(Report1!I:I,">0",Report1!D:D,A11) -> 372 | E11: =D11/B11 -> 0.86111111 | F11: =AVERAGEIFS(Report1!J:J,Report1!I:I,">0",Report1!D:D,A11) -> 189.72043
A12: Carpentry | B12: =COUNTIF(Report1!D:D,A12) -> 327 | C12: =AVERAGEIFS(Report1!L:L,Report1!L:L,">0",Report1!D:D,A12) -> 3.4225 | D12: =COUNTIFS(Report1!I:I,">0",Report1!D:D,A12) -> 283 | E12: =D12/B12 -> 0.86544343 | F12: =AVERAGEIFS(Report1!J:J,Report1!I:I,">0",Report1!D:D,A12) -> 209.82332
A13: Inspection | B13: =COUNTIF(Report1!D:D,A13) -> 46 | C13: =AVERAGEIFS(Report1!L:L,Report1!L:L,">0",Report1!D:D,A13) -> #DIV/0! | D13: =COUNTIFS(Report1!I:I,">0",Report1!D:D,A13) -> 45 | E13: =D13/B13 -> 0.97826087 | F13: =AVERAGEIFS(Report1!J:J,Report1!I:I,">0",Report1!D:D,A13) -> 37.244444
A14: Boiler | B14: =COUNTIF(Report1!D:D,A14) -> 240 | C14: =AVERAGEIFS(Report1!L:L,Report1!L:L,">0",Report1!D:D,A14) -> 392.01303 | D14: =COUNTIFS(Report1!I:I,">0",Report1!D:D,A14) -> 233 | E14: =D14/B14 -> 0.97083333 | F14: =AVERAGEIFS(Report1!J:J,Report1!I:I,">0",Report1!D:D,A14) -> 672.65236
... A33: Cleaning/Maintenance Supplies | B33: =COUNTIF(Report1!D:D,A33) -> 2 | C33: =AVERAGEIFS(Report1!L:L,Report1!L:L,">0",Report1!D:D,A33) -> #DIV/0! | D33: =COUNTIFS(Report1!I:I,">0",Report1!D:D,A33) -> 2 | E33: =D33/B33 -> 1 | F33: =AVERAGEIFS(Report1!J:J,Report1!I:I,">0",Report1!D:D,A33) -> 144

Sheet Contractors
A1: Biggest | B1: Num Contracts | C1: Avg Value | D1: Total Value | E1: Column 1
A2: rbhvacrp - 1-RBHVACRP- RBMC HVAC REPAIR | B2: 95 | C2: 454.37211 | D2: 43165.35
A3: wtorres - William Torres | B3: 134 | C3: 233.67545 | D3: 31312.51
A4: rbhvaccm - 2-BMC HVAC Contract Maintenance | B4: 18 | C4: 619.525 | D4: 11151.45
A5: riteawaypest - Rite A Way Pest Control Inc | B5: 3 | C5: 2920.6667 | D5: 8762
A6: rheing - Rheingold Gardens Apartments, L.P. | B6: 2123 | C6: 2.5949364 | D6: 5509.05
A7: aaaplaza - Triple A Plaza, LLC | B7: 113 | C7: 39.682035 | D7: 4484.07
A8: hightec - Hi-Tech Heating Corp dba Hi-Tech Heating & Cooling | B8: 51 | C8: 81.389608 | D8: 4150.87
A9: wipeout - Wipeout Exterminating LLC | B9: 30 | C9: 98.931 | D9: 2967.93
A10: safetybuild - Safety Building Cleaning Corp | B10: 2 | C10: 837.5 | D10: 1675
A11: mgservic - MG Service and Installations, Inc | B11: 45 | C11: 36.58 | D11: 1646.1
A12: universa - Universal Fireproof Door Co., Inc. | B12: 4 | C12: 341.25 | D12: 1365
A13: abco - ABCO - LONG ISLAND CITY BRANCH | B13: 2 | C13: 585 | D13: 1170
... A16: ferguson - Ferguson Enterprises, Inc | B16: 2 | C16: 405 | D16: 810
A17: rbmc - Ridgewood Bushwick Management Corp | B17: 1761 | C17: 0.43838728 | D17: 772 | E17: -Internal
A18: heights1 - Rheingold Heights One Associates L.P. | B18: 1 | C18: 674.96 | D18: 674.96 | E18: -Internal
A19: newimper - New Imperial Construction Inc. | B19: 1 | C19: 320 | D19: 320
A20: abovebey - ABOVE & BEYOND PLUMBING & HEATING Corp | B20: 23 | C20: 10.026087 | D20: 230.6
A21: rbmc2 - RiseBoro Management Corporation | B21: 288 | C21: 0.78381944 | D21: 225.74
A22: pride - PRIDE & SERVICE ELEVATOR CO., INC. | B22: 14 | C22: 12.372857 | D22: 173.22
A23: mngreenmai - M&N Green Maintenance LLC | B23: 9 | C23: 5.2222222 | D23: 47
A24: rgs - RG'S Janitorial & Home Improvement Inc. | B24: 27 | C24: 1.7325926 | D24: 46.78
A25: roofservices - Roof Services of NY a Tecta American Company | B25: 2 | C25: 22.025 | D25: 44.05
A26: bigapfir - Big Apple Fire Sprinkler Co., Inc. | B26: 9 | C26: 2.8144444 | D26: 25.33
A27: 135rb - RB 135th Avenue Owner LLC | B27: 1 | C27: 22 | D27: 22
A28: bnh - BNH Lead Examiner Corp. | B28: 11 | C28: 2 | D28: 22
A29: samthegl - Sam The Glazier Corp. | B29: 95 | C29: 0.17126316 | D29: 16.27
A30: gpscon - GPS CONSTRUCTION INC | B30: 19 | C30: 0.85526316 | D30: 16.25
... A95: libertypest - Liberty Pest Control | B95: 1 | C95: 0 | D95: 0

Sheet Copy of Report1
A1: Category | B1: Prop-Unit | C1: Status | D1: Brief Desc | E1: Tenant | F1: Call | G1: Schedule | H1: Complete | I1: Vendor | J1: Amount
A2: Plumbing | B2: rheing-533-2C | C2: Work Completed | D2: Bathroom leak/Kitchen faucet | F2: 40064.438 | H2: 40633.801 | J2: 0
A3: Appliances | B3: rheing-555-6C | C3: Work Completed | D3: Refrigerator | F3: 40064.451 | H3: 40633.803 | I3: domestic - Domestic Air Conditioning Service, Inc | J3: 0
A4: Electrical | B4: rheing-555-6C | C4: Work Completed | D4: Kitchen light/ Stove hood fan | F4: 40064.463 | H4: 40633.804 | J4: 0
A5: Painting and Plastering | B5: rheing-533-4J | C5: Work Completed | D5: Painting | F5: 40064.478 | H5: 40633.803 | I5: gpspaint - GPS Painting of NY | J5: 0
A6: Miscellaneous | B6: rheing-533-5C | C6: Work Completed | D6: Intercom | F6: 40064.494 | H6: 40633.803 | I6: mgservic - MG Service and Installations, Inc | J6: 0
A7: Miscellaneous | B7: rheing-533-4D | C7: Work Completed | D7: Bathroom soap dish | F7: 40064.498 | H7: 40633.802 | J7: 0
A8: Flooring | B8: rheing-555-6I | C8: Work Completed | D8: Bathroom tiles/light | F8: 40064.503 | H8: 40634.434 | J8: 0
A9: Miscellaneous | B9: rheing-555-5A | C9: Work Completed | D9: Intercom | F9: 40064.513 | H9: 40633.803 | I9: mgservic - MG Service and Installations, Inc | J9: 0
A10: Appliances | B10: rheing-555-2C | C10: Work Completed | D10: Refrigerator | F10: 40064.6 | H10: 40633.803 | J10: 0
A11: Plumbing | B11: rheing-533-2E | C11: Work Completed | D11: Kitchen sink | F11: 40066.668 | H11: 40106.684 | J11: 0
A12: Exterminating | B12: rheing-555-5C | C12: Work Completed | D12: MICE | E12: Morejon,Lucy | F12: 40072.435 | H12: 40085.671 | J12: 0
A13: Plumbing | B13: rheing-533-5B | C13: Work Completed | D13: PLUMBING | E13: Matias,Ramona | F13: 40072.436 | H13: 40085.672 | J13: 0
A14: Plumbing | B14: rheing-533-4F | C14: Work Completed | D14: Bathroom Sink leaking | F14: 40077.401 | H14: 40085.671 | I14: mtorres - | J14: 0
A15: Appliances | B15: rheing-533-2I | C15: Work Completed | D15: Air condition | F15: 40078.646 | H15: 40092.447 | J15: 0
A16: Plumbing | B16: rheing-533-4C | C16: Work Completed | D16: Bathroom | F16: 40079.54 | H16: 40092.465 | J16: 0
A17: Miscellaneous | B17: rheing-533-4F | C17: Work Completed | D17: Bathroom sink | F17: 40079.644 | H17: 40112.628 | J17: 0
A18: Plumbing | B18: rheing-533-4J | C18: Work Completed | D18: Bathroom/bedroom leaks | F18: 40085.531 | H18: 40130.619 | J18: 0
A19: Miscellaneous | B19: rheing-555-2D | C19: Work Completed | D19: Intercom | F19: 40085.551 | H19: 40142.514 | J19: 0
A20: Plumbing | B20: rheing-533-5C | C20: Work Completed | D20: Bathroom Leak | F20: 40085.649 | H20: 40112.629 | J20: 0
A21: Plumbing | B21: rheing-555-5C | C21: Work Completed | D21: Bathroom sink | F21: 40091.456 | H21: 40106.688 | J21: 0
A22: Miscellaneous | B22: rheing-555-6C | C22: Work Completed | D22: Bathroom | F22: 40092.421 | H22: 40106.688 | J22: 0
A23: Heating | B23: rheing-533-4E | C23: Work Completed | D23: Bedroom: heat zone valve | F23: 40095.365 | H23: 40112.629 | J23: 0
A24: Windows | B24: rheing-555-6E | C24: Work Completed | D24: Windows | F24: 40095.644 | H24: 40112.619 | J24: 0
A25: Plumbing | B25: rheing-533-4F | C25: Work Completed | D25: Bathroom Sink | F25: 40095.658 | H25: 40112.628 | J25: 0
A26: Plumbing | B26: rheing-555-5G | C26: Work Completed | D26: Bathroom toilet | F26: 40099.654 | H26: 40112.622 | J26: 0
... A37: Heating | B37: rheing-555-3D | C37: Work Completed | D37: Heat | F37: 40108.676 | H37: 40116.646 | J37: 0
A38: Appliances | B38: rheing-555-5I | C38: Work Completed | D38: REFRIGERATOR | F38: 40113.544 | H38: 40130.619 | I38: domestic - Domestic Air Conditioning Service, Inc | J38: 0
A39: Plumbing | B39: rheing-555-6A | C39: Work Completed | D39: BATHROOM SINK | F39: 40113.56 | H39: 40130.616 | J39: 0
A40: Heating | B40: rheing-555-4G | C40: Work Completed | D40: BROKEN HEATER | F40: 40116.395 | H40: 40253.687 | J40: 0
A41: Doors and Locks | B41: rheing-533-2G | C41: Work Completed | D41: LOCKS / DOORS | F41: 40116.401 | H41: 40126.408 | J41: 0
A42: Miscellaneous | B42: rheing-555-6A | C42: Work Completed | D42: BATHROOM | F42: 40116.502 | H42: 40130.616 | J42: 0
A43: Heating | B43: rheing-533-3H | C43: Work Completed | D43: HEAT | F43: 40116.505 | H43: 40130.618 | J43: 0
A44: Painting and Plastering | B44: rheing-533-2G | C44: Work Completed | D44: LIVINGROOM CEILING | F44: 40116.508 | H44: 40126.398 | J44: 0
A45: Painting and Plastering | B45: rheing-555-5C | C45: Work Completed | D45: KITCHEN WALL | F45: 40116.674 | H45: 40130.617 | J45: 0
A46: Plumbing | B46: rheing-533-2B | C46: Work Completed | D46: Leaking | F46: 40123.668 | H46: 40253.688 | J46: 0
A47: Plumbing | B47: rheing-533-2B | C47: Work Completed | D47: LEAK | E47: Mero,Martha | F47: 40127.416 | H47: 40253.688 | J47: 0
B48: rheing-533-2B | C48: Work Completed | D48: leak | E48: Mero,Martha | F48: 40130.659 | H48: 40142.515 | J48: 0
A49: Plumbing | B49: rheing-555-2D | C49: Work Completed | D49: TOILET | F49: 40134.72 | H49: 40142.515 | J49: 0
A50: Plumbing | B50: rheing-533-6J | C50: Work Completed | D50: Bathroom sink | F50: 40135.456 | H50: 40142.516 | J50: 0
A51: Plumbing | B51: rheing-533-4H | C51: Work Completed | D51: 917 620-1443 | F51: 40135.459 | H51: 40142.517 | J51: 0
A52: Plumbing | B52: rheing-555-6H | C52: Work Completed | D52: SINK | F52: 40135.512 | H52: 40142.516 | J52: 0
A53: Heating | B53: rheing-533-4E | C53: Work Completed | D53: HEAT | F53: 40135.613 | H53: 40253.688 | J53: 0
A54: Doors and Locks | B54: rheing-533-5C | C54: Work Completed | D54: DOOR LOCK | F54: 40136.722 | H54: 40155.755 | J54: 0
A55: Plumbing | B55: rheing-533-3C | C55: Work Completed | D55: SHOWER HEAD | F55: 40142.507 | H55: 40170.679 | J55: 0
A56: Heating | B56: rheing-555-2E | C56: Work Completed | D56: HEAT VALVE | F56: 40142.509 | H56: 40155.754 | J56: 0
A57: Plumbing | B57: rheing-533-4J | C57: Work Completed | D57: LEAK | F57: 40149.608 | H57: 40171.619 | J57: 0
A58: Doors and Locks | B58: rheing-555-4I | C58: Work Completed | D58: LOCKS | F58: 40149.613 | H58: 40171.62 | J58: 0
A59: Plumbing | B59: rheing-555-2A | C59: Work Completed | D59: LEAK | F59: 40149.617 | H59: 40170.679 | J59: 0
A60: Plumbing | B60: rheing-533-6I | C60: Work Completed | D60: SINK | F60: 40149.669 | H60: 40171.619 | J60: 0
... A102: Doors and Locks | B102: rheing-533-5F | C102: Work Completed | D102: LOCKS | F102: 40213.653 | H102: 40213.653 | J102: 0
B103: rheing-533-6G | C103: Work Completed | F103: 40213.656 | H103: 40213.656 | J103: 0
A104: Electrical | B104: rheing-533-5H | C104: Work Completed | D104: LIGHTS | F104: 40213.663 | H104: 40213.663 | J104: 0
A105: Miscellaneous | B105: rheing-555-6E | C105: Work Completed | D105: CULKING | F105: 40213.667 | H105: 40213.667 | J105: 0
A106: Electrical | B106: rheing-555-3H | C106: Work Completed | D106: LIGHTS | F106: 40213.67 | H106: 40213.67 | J106: 0
A107: Plumbing | B107: rheing-555-5F | C107: Work Completed | D107: LEAKS | F107: 40213.671 | H107: 40213.671 | J107: 0
B108: rheing-533-5C | C108: Work Completed | D108: REFRIGERATOR | E108: C/O Rhonda Milton,New York Foundation for Senior Citizens | F108: 40214.44 | H108: 40253.69 | J108: 0
A109: Plumbing | B109: rheing-555-5F | C109: Work Completed | D109: PIPE LOOSE IN THE BATHROOM | F109: 40217.631 | H109: 40233.581 | J109: 0
A110: Plumbing | B110: rheing-555-6I | C110: Work Completed | D110: BROKEN TOILET | F110: 40217.642 | H110: 40233.582 | J110: 0
A111: Plumbing | B111: rheing-533-5H | C111: Work Completed | D111: TOILET TANK | F111: 40219.516 | H111: 40219.516 | J111: 0
A112: Appliances | B112: rheing-555-6C | C112: Work Completed | D112: STOVE LEAKING GAS | F112: 40221.559 | H112: 40247.604 | J112: 0
A113: Miscellaneous | B113: rheing-533-4G | C113: Work Completed | D113: CULK BATHTUB | F113: 40221.592 | H113: 40247.604 | J113: 0
A114: Plumbing | B114: rheing-533-5C | C114: Work Completed | D114: SHOWER LEAKING | F114: 40227.699 | H114: 40247.604 | J114: 0
A115: Windows | B115: rheing-533-5F | C115: Work Completed | D115: BROKEN WINDOW | F115: 40228.637 | H115: 40253.69 | J115: 0
A116: Plumbing | B116: rheing-555-2C | C116: Work Completed | D116: LEAKING SINK | F116: 40233.453 | H116: 40253.69 | J116: 0
A117: Heating | B117: rheing-533-2H | C117: Work Completed | D117: HEATING LINE | F117: 40233.484 | H117: 40233.484 | J117: 0
A118: Doors and Locks | B118: rheing-533-3J | C118: Work Completed | D118: BROKEN DOOR | F118: 40233.487 | H118: 40233.487 | J118: 0
A119: Plumbing | B119: rheing-555-5D | C119: Work Completed | D119: LEAK | F119: 40240.561 | H119: 40253.691 | J119: 0
A120: Plumbing | B120: rheing-533-2B | C120: Work Completed | D120: TOILET CLOG | F120: 40241.648 | H120: 40253.691 | J120: 0
... A123: Plumbing | B123: rheing-533-2B | C123: Work Completed | D123: TOILET CLOG | F123: 40241.648 | H123: 40253.692 | J123: 0
A124: Windows | B124: rheing-533-5F | C124: Work Completed | D124: WINDOWS | F124: 40245.539 | H124: 40253.692 | I124: samthegl - Sam The Glazier Corp. | J124: 0
A125: Windows | B125: rheing | C125: Work Completed | D125: GLASS DOOR | F125: 40245.544 | H125: 40253.692 | I125: samthegl - Sam The Glazier Corp. | J125: 0
A126: Plumbing | B126: rheing-555-5H | C126: Canceled | D126: TOILET CLOG | F126: 40248.687 | J126: 0
A127: Plumbing | B127: rheing-555-3F | C127: Work Completed | D127: SHOWER HEAD | F127: 40248.69 | H127: 40259.423 | J127: 0
A128: Electrical | B128: rheing-555-5I | C128: Work Completed | D128: LIGHTS | F128: 40248.692 | H128: 40253.693 | J128: 0
A129: Electrical | B129: rheing-555-5I | C129: Work Completed | D129: LIGHTS | F129: 40248.692 | H129: 40253.693 | J129: 0
B130: rheing-533-2C | C130: Work Completed | D130: SINK | E130: Matias,Linda | F130: 40249.664 | H130: 40641.462 | J130: 0
A131: Plumbing | B131: rheing-555-2C | C131: Work Completed | D131: CLOG TUB | E131: Berroteran,Jose | F131: 40252.474 | H131: 40269.638 | J131: 0
A132: Plumbing | B132: rheing-555-5F | C132: Work Completed | D132: SINK PIPE/LEAKS/ WALL CRACKING | F132: 40254.488 | H132: 40269.637 | J132: 0
A133: Electrical | B133: rheing-555-2C | C133: Work Completed | D133: eletrical | F133: 40261.59 | H133: 40261.59 | J133: 0
A134: Electrical | B134: rheing-533-4G | C134: Work Completed | D134: Eletrical | F134: 40261.592 | H134: 40269.43 | J134: 0
A135: Doors and Locks | B135: rheing-533-6G | C135: Work Completed | D135: Door | F135: 40261.598 | H135: 40261.598 | J135: 0
A136: Electrical | B136: rheing-533-5I | C136: Work Completed | D136: eletrical | F136: 40261.6 | H136: 40261.6 | J136: 0
A137: Windows | B137: rheing-555-3D | C137: Work Completed | D137: window | F137: 40261.607 | H137: 40261.607 | J137: 0
A138: Plumbing | B138: rheing-555-2C | C138: Work Completed | D138: bathroom | F138: 40261.608 | H138: 40261.608 | J138: 0
A139: Carpentry | B139: rheing-533-2B | C139: Work Completed | D139: leak | F139: 40261.64 | H139: 40261.64 | J139: 0
A140: Plumbing | B140: rheing-533-2G | C140: Work Completed | D140: toilet | F140: 40261.653 | H140: 40261.653 | J140: 0
A141: Heating | B141: rheing-533-2C | C141: Work Completed | D141: leak | F141: 40261.655 | H141: 40261.655 | J141: 0
A142: Doors and Locks | B142: rheing-533-3J | C142: Work Completed | D142: door | F142: 40261.668 | H142: 40261.668 | J142: 0
A143: Electrical | B143: rheing-533-6G | C143: Work Completed | D143: eletrical | F143: 40261.669 | H143: 40261.669 | J143: 0
... A166: Plumbing | B166: rheing-533-6C | C166: Work Completed | D166: CLOG TOILET | F166: 40287.465 | H166: 40287.465 | J166: 0
A167: Doors and Locks | B167: rheing-533-2B | C167: Work Completed | F167: 40287.475 | H167: 40287.475 | J167: 0
A168: Flooring | B168: rheing-533-6A | C168: Work Completed | D168: TILES/CEILING | F168: 40291.561 | H168: 40312.426 | J168: 0
A169: Painting and Plastering | B169: rheing-555-5H | C169: Work Completed | D169: PAINT APT | F169: 40295.601 | H169: 40381.744 | J169: 0
A170: Doors and Locks | B170: rheing-533-4F | C170: Work Completed | D170: DOOR | F170: 40301.471 | H170: 40343.602 | J170: 0
A171: Plumbing | B171: rheing-555-3H | C171: Work Completed | D171: DRINE LINE | F171: 40308.578 | H171: 40308.578 | J171: 0
A172: Plumbing | B172: rheing-555-5F | C172: Work Completed | D172: UNCLOG SINK | F172: 40308.582 | H172: 40308.582 | J172: 0
A173: Plumbing | B173: rheing-555-3H | C173: Work Completed | D173: CLOG SINK | F173: 40308.584 | H173: 40308.584 | J173: 0
A174: Plumbing | B174: rheing-555-3G | C174: Work Completed | D174: DRAIN LINE | F174: 40308.586 | H174: 40308.586 | J174: 0
A175: Plumbing | B175: rheing-555-3G | C175: Work Completed | D175: FILL VALVE/CULK BATHROOM SINK | F175: 40308.589 | H175: 40308.589 | J175: 0
...

Sheet Pivot
A1: Column 1 | B1: Column 2 | C1: Column 3 | D1: Column 4 | E1: Column 5 | F1: Column 6 | G1: Call | H1: Schedule | I1: Complete | J1: Column 7 | K1: Column 8
A2: WO# | B2: Prop-Unit | C2: Status | D2: Category | E2: Brief Desc | F2: Tenant | G2: Date | H2: Date | I2: Date | J2: Vendor | K2: Amount
A3: 91271 | B3: rheing | C3: Work Completed | D3: Inspections | E3: 555/533 Bushwick General maintenanc | G3: 45392.661 | I3: 46051.549 | K3: 15795.28
A4: 96384 | B4: rheing | C4: Work Completed | D4: Extermination | E4: 533 ELIMINATE RODENT INFESTATION | G4: 45646.5 | I4: 45681.364 | J4: riteawaypest - Rite A Way Pest Control Inc | K4: 8761
A5: 39278 | B5: rheing | C5: Work Completed | D5: HVAC | E5: 555- Add split system | G5: 42744.664 | I5: 42791.551 | J5: wtorres - William Torres | K5: 8347.51
A6: 80660 | B6: rheing-533-2G | C6: Work Completed | D6: Heating | E6: 533 Heat Equipmt No Cover | G6: 44883.377 | I6: 45013.469 | K6: 8040.71
A7: 45243 | B7: rheing | C7: Work Completed | D7: Electrical | E7: New Electrical for HR Offices | G7: 43012.743 | I7: 43028.478 | J7: rbhvaccm - 2-BMC HVAC Contract Maintenance | K7: 3780
A8: 34879 | B8: rheing-533COMM | C8: Work Completed | D8: Lighting | E8: 555- Basement staorage Lighting | G8: 42562.614 | I8: 42636.504 | J8: wtorres - William Torres | K8: 3255
A9: 64629 | B9: rheing-533-5F | C9: Work Completed | D9: Extermination | E9: bed bug infestation | G9: 43895.343 | I9: 44498.981 | J9: wipeout - Wipeout Exterminating LLC | K9: 2962.68
A10: 79307 | B10: rheing | C10: Work Completed | D10: HVAC | E10: flood | G10: 44793.339 | I10: 44910.435 | J10: hightec - Hi-Tech Heating Corp dba Hi-Tech Heating & Cooling | K10: 2810.32
A11: 42029 | B11: rheing | C11: Work Completed | D11: Plumbing | E11: leak in bathroom | G11: 42866.4 | I11: 42872.5 | J11: rbhvacrp - 1-RBHVACRP- RBMC HVAC REPAIR | K11: 2340
A12: 72430 | B12: rheing-555-3E | C12: Work Completed | D12: Appliances | E12: oven igniter | G12: 44384.338 | I12: 45054.592 | J12: aaaplaza - Triple A Plaza, LLC | K12: 2310.2
A13: 47202 | B13: rheing | C13: Work Completed | D13: Boiler | E13: No Heat Complaints | G13: 43103.52 | I13: 43118.508 | J13: rbhvacrp - 1-RBHVACRP- RBMC HVAC REPAIR | K13: 2040
A14: 80095 | B14: rheing-533-2G | C14: Work Completed | D14: Appliances | E14: 533 Stove / Fridge | G14: 44845.42 | I14: 45006.526 | J14: rheing - Rheingold Gardens Apartments, L.P. | K14: 1990.16
A15: 41432 | B15: rheing-555-6I | C15: Work Completed | D15: Plumbing | E15: 555- leak coming from Tenant shower | G15: 42844.626 | I15: 42870.627 | J15: rbhvacrp - 1-RBHVACRP- RBMC HVAC REPAIR | K15: 1980
A16: 81068 | B16: rheing-555-4C | C16: Work Completed | D16: Appliances | E16: oven | G16: 44910.448 | I16: 45037.541 | J16: aaaplaza - Triple A Plaza, LLC | K16: 1946.02
A17: 34799 | B17: rheing | C17: Work Completed | D17: HVAC | E17: 533 A/C Nurses department | G17: 42559.487 | I17: 42615.457 | J17: wtorres - William Torres | K17: 1710
A18: 107076 | B18: rheing | C18: Work Completed | D18: Painting and Plastering | E18: Mold Removal, Surface Prep, Paint, | G18: 46129.639 | I18: 46129.639 | J18: safetybuild - Safety Building Cleaning Corp | K18: 1675
... A56: 69652 | B56: rheing | C56: Work Completed | D56: Boiler | E56: combustion air fan | G56: 44217.535 | I56: 44463.608 | J56: rbhvacrp - 1-RBHVACRP- RBMC HVAC REPAIR | K56: 682.5
A57: 83666 | B57: rheing-555-6E | C57: Work Completed | D57: Laundry | E57: Hello! Our washers and dryers have | F57: Perez,Elizabeth | G57: 45030.508 | I57: 46106.527 | J57: heights1 - Rheingold Heights One Associates L.P. | K57: 674.96
A58: 61944 | B58: rheing | C58: Work Completed | D58: Boiler | E58: no hot water dhw boiler down | G58: 43756.351 | I58: 43759.414 | J58: rbhvacrp - 1-RBHVACRP- RBMC HVAC REPAIR | K58: 656.25
A59: 36047 | B59: rheing | C59: Work Completed | D59: HVAC | E59: 533-HC-2 - A/C down | G59: 42611.417 | I59: 42613.746 | J59: wtorres - William Torres | K59: 630
A60: 37222 | B60: rheing-533COMM | C60: Work Completed | D60: Electrical | E60: 555- IT Electrical Outlets | G60: 42654.514 | I60: 42663.733 | J60: wtorres - William Torres | K60: 630
A61: 59764 | B61: rheing | C61: Work Completed | D61: HVAC | E61: Ac's in lobby not working | G61: 43654.474 | I61: 43661.387 | J61: rbhvacrp - 1-RBHVACRP- RBMC HVAC REPAIR | K61: 630
A62: 70784 | B62: rheing | C62: Work Completed | D62: Boiler | E62: 2021 Boiler Cleaning | G62: 44286.476 | I62: 44484.537 | J62: rbhvaccm - 2-BMC HVAC Contract Maintenance | K62: 563.85
A63: 33293 | B63: rheing | C63: Work Completed | D63: Plumbing | E63: leak in second floor | G63: 42488.438 | I63: 42530.673 | J63: wtorres - William Torres | K63: 540
A64: 34216 | B64: rheing | C64: Work Completed | D64: HVAC | E64: 533-AC Repair Mr Mathews office | G64: 42531.708 | I64: 42585.676 | J64: wtorres - William Torres | K64: 540
A65: 34217 | B65: rheing | C65: Work Completed | D65: HVAC | E65: 533-AC Repair Kathy Moscoso Office | G65: 42531.719 | I65: 42585.679 | J65: wtorres - William Torres | K65: 540
A66: 34361 | B66: rheing | C66: Work Completed | D66: HVAC | E66: 533-Fresh air fan tripping | G66: 42539.716 | I66: 42585.684 | J66: wtorres - William Torres | K66: 540
A67: 37196 | B67: rheing | C67: Work Completed | D67: Boiler | E67: 533- motor # 1 tripping breaker | G67: 42654.402 | I67: 42664.763 | J67: wtorres - William Torres | K67: 540
A68: 38865 | B68: rheing-533COMM | C68: Work Completed | D68: Heating | E68: Thermostat adjustmments | G68: 42720.562 | I68: 42766.674 | J68: wtorres - William Torres | K68: 540
A69: 39174 | B69: rheing | C69: Work Completed | D69: HVAC | E69: Server Room AC down | G69: 42739.484 | I69: 42766.448 | J69: wtorres - William Torres | K69: 540
... A122: 39690 | B122: rheing | C122: Work Completed | D122: HVAC | E122: 555- Server room AC down | G122: 42762.473 | I122: 42780.533 | J122: wtorres - William Torres | K122: 270
A123: 42189 | B123: rheing | C123: Work Completed | D123: HVAC | E123: 533- Lobby AC down. | G123: 42873.671 | H123: 42874.296 | I123: 42935.544 | J123: rbhvacrp - 1-RBHVACRP- RBMC HVAC REPAIR | K123: 270
A124: 46532 | B124: rheing-533COMM | C124: Work Completed | D124: HVAC | E124: Server Room AC Down | G124: 43069.676 | I124: 43126.682 | J124: rbhvacrp - 1-RBHVACRP- RBMC HVAC REPAIR | K124: 270
A125: 54062 | B125: rheing | C125: Work Completed | D125: Boiler | E125: 555-Boiler #3 Pressure valve | G125: 43389.843 | I125: 43452.701 | J125: rbhvacrp - 1-RBHVACRP- RBMC HVAC REPAIR | K125: 270
A126: 54717 | B126: rheing | C126: Work Completed | D126: Boiler | E126: 555-boiler#1- Flow switch | G126: 43419.588 | I126: 43452.699 | J126: rbhvacrp - 1-RBHVACRP- RBMC HVAC REPAIR | K126: 270
A127: 59472 | B127: rheing | C127: Work Completed | D127: HVAC | E127: 2019 AC - Service and Cleaning | G127: 43635.529 | I127: 43637.659 | J127: rbhvaccm - 2-BMC HVAC Contract Maintenance | K127: 270
A128: 59473 | B128: rheing-533COMM | C128: Work Completed | D128: HVAC | E128: 2019 AC - Service and Cleaning | G128: 43635.536 | I128: 43637.66 | J128: rbhvaccm - 2-BMC HVAC Contract Maintenance | K128: 270
A129: 81370 | B129: rheing | C129: Work Completed | D129: HVAC | E129: Leak from AC system | G129: 44931.354 | I129: 45017.521 | J129: rbhvacrp - 1-RBHVACRP- RBMC HVAC REPAIR | K129: 270
A130: 83893 | B130: rheing | C130: Work Completed | D130: HVAC | E130: To hot in office | G130: 45042.41 | I130: 45082.481 | J130: rbhvacrp - 1-RBHVACRP- RBMC HVAC REPAIR | K130: 270
A131: 77954 | B131: rheing | C131: Work Completed | D131: Boiler | E131: leaking pipe | G131: 44705.361 | I131: 44725.603 | J131: rbhvacrp - 1-RBHVACRP- RBMC HVAC REPAIR | K131: 262.5
A132: 78815 | B132: rheing | C132: Work Completed | D132: Boiler | E132: annual Boiler cleaning 2022 | G132: 44763.64 | I132: 44846.345 | J132: rbhvaccm - 2-BMC HVAC Contract Maintenance | K132: 254.1
A133: 38089 | B133: rheing | C133: Work Completed | D133: HVAC | E133: 533- Thermostat settings | G133: 42688.688 | I133: 42760.731 | J133: wtorres - William Torres | K133: 225
A134: 38090 | B134: rheing-533COMM | C134: Work Completed | D134: HVAC | E134: 555-Thermostat seetings | G134: 42688.693 | I134: 42776.588 | J134: wtorres - William Torres | K134: 225
A135: 67025 | B135: rheing | C135: Work Completed | D135: Elevator | E135: 585 Bushwick door monitoring lock | G135: 44063.583 | I135: 44063.603 | J135: rheing - Rheingold Gardens Apartments, L.P. | K135: 223
A136: 60156 | B136: rheing | C136: Canceled | D136: HVAC | E136: 1st and 2nd floor AC issues | G136: 43670.501 | J136: rbhvacrp - 1-RBHVACRP- RBMC HVAC REPAIR | K136: 210
A137: 61497 | B137: rheing-533-3A | C137: Work Completed | D137: Plumbing | E137: broken Faucets | G137: 43735.471 | I137: 43742.641 | J137: rbhvacrp - 1-RBHVACRP- RBMC HVAC REPAIR | K137: 210
A138: 66593 | B138: rheing-533-5B | C138: Work Completed | D138: Plumbing | E138: shower body | G138: 44039.435 | I138: 44046.466 | J138: rheing - Rheingold Gardens Apartments, L.P. | K138: 210
A139: 76189 | B139: rheing | C139: Work Completed | D139: Boiler | E139: no heat at 565 | G139: 44600.355 | I139: 44713.688 | J139: rbhvacrp - 1-RBHVACRP- RBMC HVAC REPAIR | K139: 210
A140: 80389 | B140: rheing | C140: Work Completed | D140: HVAC | E140: Over heating Office | G140: 44865.478 | I140: 44934.781 | J140: rbhvacrp - 1-RBHVACRP- RBMC HVAC REPAIR | K140: 210
A141: 53051 | B141: rheing | C141: Work Completed | D141: Boiler | E141: Circulation pump | G141: 43354.366 | I141: 43446.465 | J141: rbhvacrp - 1-RBHVACRP- RBMC HVAC REPAIR | K141: 206.25
A142: 82667 | B142: rheing | C142: Work Completed | D142: Boiler | E142: Annual Boiler Cleaning | G142: 44993.614 | I142: 45119.411 | J142: rbhvacrp - 1-RBHVACRP- RBMC HVAC REPAIR | K142: 202.5
A143: 82669 | B143: rheing | C143: Work Completed | D143: Boiler | E143: Annual Boiler Cleaning | G143: 44993.617 | I143: 45119.407 | J143: rbhvacrp - 1-RBHVACRP- RBMC HVAC REPAIR | K143: 202.5
A144: 84611 | B144: rheing | C144: Work Completed | D144: HVAC | E144: Annual AC Cleaning | G144: 45070.661 | I144: 45119.417 | J144: rbhvacrp - 1-RBHVACRP- RBMC HVAC REPAIR | K144: 202.5
A145: 59212 | B145: rheing-533-6J | C145: Work Completed | D145: Appliances | E145: oven | G145: 43624.746 | I145: 43664.536 | J145: joab - JOAB Appliance Service | K145: 199
A146: 55825 | B146: rheing-533-4E | C146: Work Completed | D146: Heating | E146: Door damaged | G146: 43480.624 | I146: 43654.662 | J146: rbmc2 - RiseBoro Management Corporation | K146: 195
A147: 34059 | B147: rheing | C147: Work Completed | D147: Boiler | E147: 555 Boiler Burner Check | G147: 42523.417 | I147: 42779.459 | J147: wtorres - William Torres | K147: 180
A148: 34076 | B148: rheing | C148: Work Completed | D148: Boiler | E148: 533 -Boiler Burner Check | G148: 42524.369 | I148: 42779.458 | J148: wtorres - William Torres | K148: 180
... A157: 68629 | B157: rheing | C157: Work Completed | D157: Boiler | E157: no heat | G157: 44153.554 | I157: 44169.329 | J157: rbhvacrp - 1-RBHVACRP- RBMC HVAC REPAIR | K157: 160.65
A158: 41753 | B158: rheing | C158: Canceled | D158: Plumbing | E158: leak in case management | G158: 42856.577 | J158: rbhvacrp - 1-RBHVACRP- RBMC HVAC REPAIR | K158: 157.5
A159: 59000 | B159: rheing | C159: Work Completed | D159: HVAC | E159: 533 HC- AC- Ptac leak | G159: 43616.572 | I159: 43620.614 | J159: rbhvacrp - 1-RBHVACRP- RBMC HVAC REPAIR | K159: 157.5
A160: 59038 | B160: rheing-533COMM | C160: Work Completed | D160: HVAC | E160: 533-AC Noise and repair | G160: 43619.496 | I160: 43621.409 | J160: rbhvacrp - 1-RBHVACRP- RBMC HVAC REPAIR | K160: 157.5
A161: 60042 | B161: rheing | C161: Work Completed | D161: HVAC | E161: Air vents in office space not worki | G161: 43664.387 | I161: 44497.683 | J161: hightec - Hi-Tech Heating Corp dba Hi-Tech Heating & Cooling | K161: 157.5
A162: 60883 | B162: rheing | C162: Work Completed | D162: HVAC | E162: Air conditioner not working | G162: 43703.633 | I162: 43717.664 | J162: rbhvacrp - 1-RBHVACRP- RBMC HVAC REPAIR | K162: 157.5
A163: 61218 | B163: rheing | C163: Work Completed | D163: HVAC | E163: leaking A/C Comm space | G163: 43719.562 | I163: 43731.633 | J163: rbhvacrp - 1-RBHVACRP- RBMC HVAC REPAIR | K163: 157.5
A164: 62340 | B164: rheing | C164: Work Completed | D164: Heating | E164: 555 Bushwick no heat | G164: 43773.461 | I164: 43783.569 | J164: abovebey - ABOVE & BEYOND PLUMBING & HEATING Corp | K164: 157.5
A165: 62671 | B165: rheing | C165: Work Completed | D165: HVAC | E165: IT Server room AC down | G165: 43790.397 | I165: 43795.474 | J165: rbhvacrp - 1-RBHVACRP- RBMC HVAC REPAIR | K165: 157.5
A166: 68338 | B166: rheing | C166: Work Completed | D166: Boiler | E166: heating boiler | G166: 44137.3 | I166: 44159.586 | J166: rbhvacrp - 1-RBHVACRP- RBMC HVAC REPAIR | K166: 157.5
A167: 74188 | B167: rheing | C167: Work Completed | D167: Heating | E167: no heat | G167: 44488.241 | I167: 44657.512 | J167: rbhvacrp - 1-RBHVACRP- RBMC HVAC REPAIR | K167: 157.5
A168: 76772 | B168: rheing | C168: Work Completed | D168: Boiler | E168: No Heat complaint | G168: 44634.676 | I168: 44719.632 | J168: rbhvacrp - 1-RBHVACRP- RBMC HVAC REPAIR | K168: 157.5
A169: 77104 | B169: rheing-533-6F | C169: Work Completed | D169: Boiler | E169: no hot water | G169: 44655.818 | I169: 44673.579 | J169: rbhvacrp - 1-RBHVACRP- RBMC HVAC REPAIR | K169: 157.5
A170: 59499 | B170: rheing | C170: Work Completed | D170: Boiler | E170: circulation pump Relay | G170: 43636.486 | I170: 43892.581 | J170: rbhvacrp - 1-RBHVACRP- RBMC HVAC REPAIR | K170: 150
... A202: 90367 | B202: rheing-533-1A | C202: Work Completed | D202: Apt. Prep. | E202: 533 Bushwick super unit | G202: 45352.716 | I202: 46105.532 | J202: rheing - Rheingold Gardens Apartments, L.P. | K202: 22
A203: 96618 | B203: rheing-555-5F | C203: Work Completed | D203: Heating | E203: 555- There is not enough heat | F203: Rivera,Marielita | G203: 45664.54 | I203: 46106.512 | J203: 135rb - RB 135th Avenue Owner LLC | K203: 22
A204: 106039 | B204: rheing | C204: Work Completed | D204: Doors and Locks | E204: Main entrance door handle broke off. | G204: 46098.666 | I204: 46106.666 | J204: rheing - Rheingold Gardens Apartments, L.P. | K204: 20
A205: 81363 | B205: rheing-533-6G | C205: Work Completed | D205: Heating | E205: thermostat not working | F205: Excell,Gladstone | G205: 44930.635 | I205: 46106.518 | J205: rheing - Rheingold Gardens Apartments, L.P. | K205: 16.5
A206: 81189 | B206: rheing | C206: Work Completed | D206: Plumbing | E206: leak in the ceiling | G206: 44917.397 | I206: 44957.408 | J206: abovebey - ABOVE & BEYOND PLUMBING & HEATING Corp | K206: 16.33
A207: 69408 | B207: rheing | C207: Work Completed | D207: Plumbing | E207: leak in boiler room Copper pipe | G207: 44202.379 | I207: 44216.599 | J207: rbmc2 - RiseBoro Management Corporation | K207: 16
A208: 72603 | B208: rheing | C208: Work Completed | D208: Elevator | E208: new seal for piston | G208: 44392.592 | I208: 44392.594 | J208: pride - PRIDE & SERVICE ELEVATOR CO., INC. | K208: 16
A209: 98074 | B209: rheing-555-5A | C209: Work Completed | D209: Fire Safety | E209: 555 Combo - CO/SD | F209: Rivera,Carmen | G209: 45732.517 | I209: 45793.397 | J209: rheing - Rheingold Gardens Apartments, L.P. | K209: 16
A210: 86360 | B210: rheing | C210: Work Completed | D210: Plumbing | E210: leak in basement 555 | G210: 45154.422 | I210: 46106.643 | J210: rheing - Rheingold Gardens Apartments, L.P. | K210: 14.74
A211: 89355 | B211: rheing | C211: Work Completed | D211: Lockout | E211: Front door lock is broken | G211: 45311.382 | I211: 45311.431 | J211: southbronxre - South Bronx Restoration, LLC | K211: 13
A212: 65769 | B212: rheing | C212: Work Completed | D212: Boiler | E212: DHW not working | G212: 43991.612 | I212: 43991.616 | J212: hightec - Hi-Tech Heating Corp dba Hi-Tech Heating & Cooling | K212: 9
A213: 72548 | B213: rheing-555-4D | C213: Work Completed | D213: Appliances | E213: refrigerator leaking | F213: Romero,Maria | G213: 44390.445 | I213: 44686.518 | J213: aaaplaza - Triple A Plaza, LLC | K213: 9
A214: 75099 | B214: rheing-555-4H | C214: Work Completed | D214: Carpentry | E214: countertop needs to be replaced | G214: 44540.461 | I214: 44540.461 | J214: rheing - Rheingold Gardens Apartments, L.P. | K214: 9
A215: 76195 | B215: rheing | C215: Work Completed | D215: Plumbing | E215: leak in ceiling of garage | G215: 44600.399 | I215: 44629.413 | J215: rgs - RG'S Janitorial & Home Improvement Inc. | K215: 9
A216: 77081 | B216: rheing-533-6F | C216: Work Completed | D216: Painting and Plastering | E216: bathroom mold | G216: 44655.413 | I216: 44680.414 | J216: bnh - BNH Lead Examiner Corp. | K216: 9
A217: 81346 | B217: rheing | C217: Work Completed | D217: Elevator | E217: DOORS NOT OPENING ON 5TH FLOOR | G217: 44930.429 | I217: 44930.428 | J217: pride - PRIDE & SERVICE ELEVATOR CO., INC. | K217: 9
A218: 84553 | B218: rheing | C218: Work Completed | D218: Extermination | E218: 535 office-bedbugs | G218: 45069.359 | I218: 45069.362 | J218: teamp1 - Team Pest Control International, Inc. | K218: 9
A219: 87435 | B219: rheing-555-2C | C219: Work Completed | D219: Carpentry | E219: cabinets need to be replaced | F219: Berroteran,Jose | G219: 45211.401 | I219: 45247.569 | J219: bnh - BNH Lead Examiner Corp. | K219: 9
A220: 90616 | B220: rheing-533-2J | C220: In Progress | D220: Inspections | E220: 533 apt. 2J window water leak | G220: 45363.499 | K220: 7.4
A221: 75731 | B221: rheing | C221: Work Completed | D221: Plumbing | E221: Circulating DHW | G221: 44580.734 | I221: 44593.379 | J221: hightec - Hi-Tech Heating Corp dba Hi-Tech Heating & Cooling | K221: 6.5
A222: 75072 | B222: rheing-533-2E | C222: Work Completed | D222: Carpentry | E222: countertops were replaced | G222: 44539.513 | I222: 44539.513 | J222: rheing - Rheingold Gardens Apartments, L.P. | K222: 6
A223: 57901 | B223: rheing-533-4A | C223: Work Completed | D223: Apt. Prep. | E223: paint | G223: 43566.528 | I223: 43714.46 | J223: rbmc2 - RiseBoro Management Corporation | K223: 5
A224: 65936 | B224: rheing | C224: Work Completed | D224: Fire Safety | E224: alarm continues to go off | G224: 44000.652 | I224: 44000.651 | J224: safe - Casey Fire Systems INC | K224: 4.25
A225: 94924 | B225: rheing-555-6I | C225: Work Completed | D225: Painting and Plastering | E225: 555 Bushwick 6I ceiling painting | G225: 45572.567 | I225: 45678.468 | J225: gpscon - GPS CONSTRUCTION INC | K225: 4.25
A226: 61166 | B226: rheing-533-2E | C226: Work Completed | D226: Carpentry | E226: counter top | G226: 43715.767 | I226: 44539.556 | J226: rheing - Rheingold Gardens Apartments, L.P. | K226: 4
A227: 67012 | B227: rheing-555-3E | C227: Work Completed | D227: Windows | E227: window pane in living room cracked | F227: Reina,Claribel | G227: 44063.455 | I227: 44071.615 | J227: samthegl - Sam The Glazier Corp. | K227: 4
A228: 67129 | B228: rheing | C228: Work Completed | D228: HVAC | E228: A/C line | G228: 44069.636 | I228: 44071.376 | J228: rheing - Rheingold Gardens Apartments, L.P. | K228: 4
...

Sheet Sheet1
A1: Prop-Unit | B1: Status | C1: Category | D1: Brief Desc | E1: Tenant | F1: Call | G1: Schedule | H1: Complete | I1: Vendor | J1: Amount
A2: =IFERROR(__xludf.DUMMYFUNCTION("COUNTUNIQUE(Report1!B$3:B$6181)"),95.0) -> 95 | B2: =IFERROR(__xludf.DUMMYFUNCTION("COUNTUNIQUE(Report1!C$3:C$6181)"),7.0) -> 7 | C2: =IFERROR(__xludf.DUMMYFUNCTION("COUNTUNIQUE(Report1!D$3:D$6181)"),32.0) -> 32 | D2: =IFERROR(__xludf.DUMMYFUNCTION("COUNTUNIQUE(Report1!E$3:E$6181)"),4302.0) -> 4302 | E2: =IFERROR(__xludf.DUMMYFUNCTION("COUNTUNIQUE(Report1!F$3:F$6181)"),86.0) -> 86 | F2: =IFERROR(__xludf.DUMMYFUNCTION("COUNTUNIQUE(Report1!G$3:G$6181)"),5995.0) -> 5995 | G2: =IFERROR(__xludf.DUMMYFUNCTION("COUNTUNIQUE(Report1!H$3:H$6181)"),94.0) -> 94 | H2: =IFERROR(__xludf.DUMMYFUNCTION("COUNTUNIQUE(Report1!I$3:I$6181)"),5096.0) -> 5096 | I2: =IFERROR(__xludf.DUMMYFUNCTION("COUNTUNIQUE(Report1!K$3:K$6181)"),94.0) -> 94 | J2: =IFERROR(__xludf.DUMMYFUNCTION("COUNTUNIQUE(Report1!L$3:L$6181)"),152.0) -> 152
